deepagents/__init__.py
deepagents/builder.py
deepagents/graph.py
deepagents/interrupt.py
deepagents/model.py
deepagents/prompts.py
deepagents/state.py
deepagents/sub_agent.py
deepagents/tools.py
new_deepagents-0.0.5.4.dist-info/licenses/LICENSE
new_deepagents-0.0.5.4.dist-info/METADATA
new_deepagents-0.0.5.4.dist-info/WHEEL
new_deepagents-0.0.5.4.dist-info/top_level.txt
new_deepagents-0.0.5.4.dist-info/RECORD
