Metadata-Version: 2.4
Name: new-deepagents
Version: 0.0.5.4
Summary: General purpose 'deep agent' with sub-agent spawning, todo list capabilities, and mock file system. Built on LangGraph.
License: MIT
Requires-Python: <4.0,>=3.11
License-File: LICENSE
Requires-Dist: langgraph>=0.2.6
Requires-Dist: langchain-anthropic>=0.1.23
Requires-Dist: langchain>=0.2.14
Dynamic: license-file
